jupyterlab_refresh_view_extension/__init__.py
jupyterlab_refresh_view_extension/_version.py
jupyterlab_refresh_view_extension-1.2.19.data/data/share/jupyter/labextensions/jupyterlab_refresh_view_extension/package.json
jupyterlab_refresh_view_extension-1.2.19.data/data/share/jupyter/labextensions/jupyterlab_refresh_view_extension/schemas/jupyterlab_refresh_view_extension/package.json.orig
jupyterlab_refresh_view_extension-1.2.19.data/data/share/jupyter/labextensions/jupyterlab_refresh_view_extension/schemas/jupyterlab_refresh_view_extension/plugin.json
jupyterlab_refresh_view_extension-1.2.19.data/data/share/jupyter/labextensions/jupyterlab_refresh_view_extension/static/509.674f427f6e383715352e.js
jupyterlab_refresh_view_extension-1.2.19.data/data/share/jupyter/labextensions/jupyterlab_refresh_view_extension/static/728.130fe2a94ea19093a146.js
jupyterlab_refresh_view_extension-1.2.19.data/data/share/jupyter/labextensions/jupyterlab_refresh_view_extension/static/remoteEntry.ed0013a7907fd689a59d.js
jupyterlab_refresh_view_extension-1.2.19.data/data/share/jupyter/labextensions/jupyterlab_refresh_view_extension/static/style.js
jupyterlab_refresh_view_extension-1.2.19.data/data/share/jupyter/labextensions/jupyterlab_refresh_view_extension/static/third-party-licenses.json
jupyterlab_refresh_view_extension-1.2.19.data/data/share/jupyter/labextensions/jupyterlab_refresh_view_extension/install.json
jupyterlab_refresh_view_extension-1.2.19.dist-info/METADATA
jupyterlab_refresh_view_extension-1.2.19.dist-info/WHEEL
jupyterlab_refresh_view_extension-1.2.19.dist-info/licenses/LICENSE
jupyterlab_refresh_view_extension-1.2.19.dist-info/RECORD
