Metadata-Version: 2.4
Name: jupyterlab_refresh_view_extension
Version: 1.2.19
Summary: JupyterLab extension adding context menu 'Refresh View' command to reload file content from disk while preserving scroll position
Project-URL: Homepage, https://github.com/the-cog-conf/jupyterlab_refresh_view_extension
Project-URL: Bug Tracker, https://github.com/the-cog-conf/jupyterlab_refresh_view_extension/issues
Project-URL: Repository, https://github.com/the-cog-conf/jupyterlab_refresh_view_extension.git
Author-email: Stellars Henson <konrad.jelen@gmail.com>
License: BSD 3-Clause License
License-File: LICENSE
Keywords: jupyter,jupyterlab,jupyterlab-extension
Classifier: Framework :: Jupyter
Classifier: Framework :: Jupyter :: JupyterLab
Classifier: Framework :: Jupyter :: JupyterLab :: 4
Classifier: Framework :: Jupyter :: JupyterLab :: Extensions
Classifier: Framework :: Jupyter :: JupyterLab :: Extensions :: Prebuilt
Classifier: License :: OSI Approved :: BSD License
Classifier: Programming Language :: Python
Classifier: Programming Language :: Python :: 3
Classifier: Programming Language :: Python :: 3.9
Classifier: Programming Language :: Python :: 3.10
Classifier: Programming Language :: Python :: 3.11
Classifier: Programming Language :: Python :: 3.12
Classifier: Programming Language :: Python :: 3.13
Requires-Python: >=3.9
